sqlmasker/sqlmakser.py
sqlmasker-0.1.0.dist-info/WHEEL
sqlmasker-0.1.0.dist-info/METADATA
sqlmasker-0.1.0.dist-info/RECORD
