Metadata-Version: 2.1
Name: sqlmasker
Version: 0.1.0
Summary: n
Author: Cazqew Powered
Author-email: nikprotect@protonmail.com
Requires-Python: >=3.7,<4.0
Classifier: Programming Language :: Python :: 3
Classifier: Programming Language :: Python :: 3.10
Classifier: Programming Language :: Python :: 3.7
Classifier: Programming Language :: Python :: 3.8
Classifier: Programming Language :: Python :: 3.9
